{
  "_note": "Baseline placeholder. Replace by running __phonaraSurface.entropy() in a DEV browser console after ~5min on /dashboard. Expected untracked > 0 (≈70+ legacy setInterval call sites caught by the DEV override).",
  "capturedAt": null,
  "counts":     { "tracked": 0, "untracked": 0, "total": 0, "coverage": 0 },
  "byCategory": {
    "money_flow": { "tracked": 0, "untracked": 0 },
    "cosmetic":   { "tracked": 0, "untracked": 0 },
    "admin":      { "tracked": 0, "untracked": 0 },
    "unknown":    { "tracked": 0, "untracked": 0 }
  },
  "tracked":   [],
  "untracked": []
}
